recon/__init__.py
recon/augmentation.py
recon/cli/__init__.py
recon/cli/_util.py
recon/cli/dashboard.py
recon/cli/stats.py
recon/constants.py
recon/corpus.py
recon/corrections.py
recon/dataset.py
recon/hashing.py
recon/insights.py
recon/linker.py
recon/loaders.py
recon/operations.py
recon/preprocess.py
recon/prodigy/__init__.py
recon/prodigy/recipes.py
recon/prodigy/templates/prediction_error.html
recon/prodigy/utils.py
recon/recognizer.py
recon/sample.py
recon/scorer.py
recon/stats.py
recon/store.py
recon/tokenization.py
recon/types.py
recon/util.py
recon/validation.py
reconner-0.14.0.dist-info/LICENSE
reconner-0.14.0.dist-info/METADATA
reconner-0.14.0.dist-info/WHEEL
reconner-0.14.0.dist-info/entry_points.txt
reconner-0.14.0.dist-info/RECORD
