Metadata-Version: 2.1
Name: reconner
Version: 0.14.0
Summary: Recon NER, Debug and correct annotated Named Entity Recognition (NER) data for inconsitencies and get insights on improving the quality of your data.
Home-page: https://kabirkhan.github.io/recon
Author: Kabir Khan
Author-email: kabirkhan1137@outlook.com
Requires-Python: >=3.8,<3.12
Classifier: Development Status :: 4 - Beta
Classifier: Intended Audience :: Developers
Classifier: Intended Audience :: Information Technology
Classifier: Intended Audience :: System Administrators
Classifier: License :: OSI Approved :: MIT License
Classifier: Operating System :: OS Independent
Classifier: Programming Language :: Python
Classifier: Programming Language :: Python :: 3
Classifier: Programming Language :: Python :: 3.8
Classifier: Programming Language :: Python :: 3.9
Classifier: Programming Language :: Python :: 3.10
Classifier: Programming Language :: Python :: 3.11
Classifier: Programming Language :: Python :: 3 :: Only
Classifier: Topic :: Software Development
Classifier: Topic :: Software Development :: Libraries
Classifier: Topic :: Software Development :: Libraries :: Application Frameworks
Classifier: Topic :: Software Development :: Libraries :: Python Modules
Classifier: Typing :: Typed
Provides-Extra: hf
Provides-Extra: jupyter
Provides-Extra: plot
Requires-Dist: click-completion
Requires-Dist: colorama
Requires-Dist: numpy (>=1.20.0)
Requires-Dist: pydantic (>=2.0,<3.0)
Requires-Dist: radicli (>0.0.8,<0.1)
Requires-Dist: scipy (>=1.7.0,<2.0)
Requires-Dist: spacy (>=3.2.0,<4.0)
Requires-Dist: xxhash (>=3.0.0,<4.0)
Project-URL: Documentation, https://kabirkhan.github.io/recon
Project-URL: Repository, https://github.com/kabirkhan/recon
